geosoft/__init__.py
geosoft/pkg_info.json
geosoft/gxapi/GX3DC.py
geosoft/gxapi/GX3DN.py
geosoft/gxapi/GX3DV.py
geosoft/gxapi/GXACQUIRE.py
geosoft/gxapi/GXAGG.py
geosoft/gxapi/GXARCDB.py
geosoft/gxapi/GXARCDH.py
geosoft/gxapi/GXARCMAP.py
geosoft/gxapi/GXARCPY.py
geosoft/gxapi/GXARCSYS.py
geosoft/gxapi/GXBF.py
geosoft/gxapi/GXBIGRID.py
geosoft/gxapi/GXCHIMERA.py
geosoft/gxapi/GXCOM.py
geosoft/gxapi/GXCSYMB.py
geosoft/gxapi/GXCSYMB3D.py
geosoft/gxapi/GXContext.py
geosoft/gxapi/GXDAT.py
geosoft/gxapi/GXDATALINKD.py
geosoft/gxapi/GXDATAMINE.py
geosoft/gxapi/GXDB.py
geosoft/gxapi/GXDBREAD.py
geosoft/gxapi/GXDBWRITE.py
geosoft/gxapi/GXDCOL.py
geosoft/gxapi/GXDGW.py
geosoft/gxapi/GXDH.py
geosoft/gxapi/GXDMPPLY.py
geosoft/gxapi/GXDOCU.py
geosoft/gxapi/GXDSEL.py
geosoft/gxapi/GXDU.py
geosoft/gxapi/GXDXFI.py
geosoft/gxapi/GXE3DV.py
geosoft/gxapi/GXEDB.py
geosoft/gxapi/GXEDOC.py
geosoft/gxapi/GXEMAP.py
geosoft/gxapi/GXEMAPTEMPLATE.py
geosoft/gxapi/GXEUL3.py
geosoft/gxapi/GXEVOOBJMETA.py
geosoft/gxapi/GXEXP.py
geosoft/gxapi/GXEXT.py
geosoft/gxapi/GXFFT.py
geosoft/gxapi/GXFFT2.py
geosoft/gxapi/GXFLT.py
geosoft/gxapi/GXGD.py
geosoft/gxapi/GXGEOSTRING.py
geosoft/gxapi/GXGER.py
geosoft/gxapi/GXGIS.py
geosoft/gxapi/GXGMSYS.py
geosoft/gxapi/GXGRID3D.py
geosoft/gxapi/GXGU.py
geosoft/gxapi/GXGUI.py
geosoft/gxapi/GXHGD.py
geosoft/gxapi/GXHTTP.py
geosoft/gxapi/GXHXYZ.py
geosoft/gxapi/GXIEXP.py
geosoft/gxapi/GXIGRF.py
geosoft/gxapi/GXIMG.py
geosoft/gxapi/GXIMU.py
geosoft/gxapi/GXINTERNET.py
geosoft/gxapi/GXIP.py
geosoft/gxapi/GXIPGUI.py
geosoft/gxapi/GXIPJ.py
geosoft/gxapi/GXITR.py
geosoft/gxapi/GXKGRD.py
geosoft/gxapi/GXKML.py
geosoft/gxapi/GXLAYOUT.py
geosoft/gxapi/GXLL2.py
geosoft/gxapi/GXLMSG.py
geosoft/gxapi/GXLPT.py
geosoft/gxapi/GXLST.py
geosoft/gxapi/GXLTB.py
geosoft/gxapi/GXMAP.py
geosoft/gxapi/GXMAPL.py
geosoft/gxapi/GXMAPTEMPLATE.py
geosoft/gxapi/GXMATH.py
geosoft/gxapi/GXMESH.py
geosoft/gxapi/GXMESHUTIL.py
geosoft/gxapi/GXMETA.py
geosoft/gxapi/GXMISC.py
geosoft/gxapi/GXMPLY.py
geosoft-2025.2.0.dist-info/LICENSE
geosoft-2025.2.0.dist-info/METADATA
geosoft-2025.2.0.dist-info/WHEEL
geosoft-2025.2.0.dist-info/top_level.txt
geosoft-2025.2.0.dist-info/RECORD
