Metadata-Version: 2.1
Name: geosoft
Version: 2025.2.0
Summary: Geosoft GX API module for Python
Home-page: https://github.com/GeosoftInc/gxpy
Author: Geosoft Inc.
Author-email: support@geosoft.com
License: BSD
Platform: win_amd64
Classifier: Development Status :: 5 - Production/Stable
Classifier: Topic :: Scientific/Engineering
Classifier: Intended Audience :: Science/Research
Classifier: License :: OSI Approved :: BSD License
Classifier: Natural Language :: English
Classifier: Operating System :: Microsoft :: Windows
Classifier: Programming Language :: Python :: 3 :: Only
License-File: LICENSE
Requires-Dist: pandas>=2.2.3
Requires-Dist: requests>=2.31.0
Requires-Dist: jdcal>=1.3
Requires-Dist: setuptools>=75.8.0
Requires-Dist: numpy>=2.2.1
